<?xml version="1.0" encoding="utf-8"?>
<ConfigObjC xmlns:xsi="http://www.w3.org/2001/XMLSchema-instance" xmlns:xsd="http://www.w3.org/2001/XMLSchema">
<!--

-->
    <TypeNameSkipList>
        <string>System.Drawing.Bitmap</string>
        <string>System.Drawing.BitmapSuffixInSameAssemblyAttribute</string>
        <string>System.Drawing.BitmapSuffixInSatelliteAssemblyAttribute</string>
        <string>System.Drawing.Brush</string>
        <string>System.Drawing.Brushes</string>
        <string>System.Drawing.BufferedGraphics</string>
        <string>System.Drawing.BufferedGraphicsContext</string>
        <string>System.Drawing.BufferedGraphicsManager</string>
        <string>System.Drawing.CharacterRange</string>
        <string>System.Drawing.Color</string>
        <string>System.Drawing.ColorConverter</string>
        <string>System.Drawing.ColorTranslator</string>
        <string>System.Drawing.Configuration.SystemDrawingSection</string>
        <string>System.Drawing.ContentAlignment</string>
        <string>System.Drawing.CopyPixelOperation</string>
        <string>System.Drawing.Design.CategoryNameCollection</string>
        <string>System.Drawing.Design.IPropertyValueUIService</string>
        <string>System.Drawing.Design.IToolboxItemProvider</string>
        <string>System.Drawing.Design.IToolboxService</string>
        <string>System.Drawing.Design.IToolboxUser</string>
        <string>System.Drawing.Design.PaintValueEventArgs</string>
        <string>System.Drawing.Design.PropertyValueUIHandler</string>
        <string>System.Drawing.Design.PropertyValueUIItem</string>
        <string>System.Drawing.Design.PropertyValueUIItemInvokeHandler</string>
        <string>System.Drawing.Design.ToolboxComponentsCreatedEventArgs</string>
        <string>System.Drawing.Design.ToolboxComponentsCreatedEventHandler</string>
        <string>System.Drawing.Design.ToolboxComponentsCreatingEventArgs</string>
        <string>System.Drawing.Design.ToolboxComponentsCreatingEventHandler</string>
        <string>System.Drawing.Design.ToolboxItem</string>
        <string>System.Drawing.Design.ToolboxItemCollection</string>
        <string>System.Drawing.Design.ToolboxItemCreatorCallback</string>
        <string>System.Drawing.Design.UITypeEditor</string>
        <string>System.Drawing.Design.UITypeEditorEditStyle</string>
        <string>System.Drawing.Drawing2D.AdjustableArrowCap</string>
        <string>System.Drawing.Drawing2D.Blend</string>
        <string>System.Drawing.Drawing2D.ColorBlend</string>
        <string>System.Drawing.Drawing2D.CombineMode</string>
        <string>System.Drawing.Drawing2D.CompositingMode</string>
        <string>System.Drawing.Drawing2D.CompositingQuality</string>
        <string>System.Drawing.Drawing2D.CoordinateSpace</string>
        <string>System.Drawing.Drawing2D.CustomLineCap</string>
        <string>System.Drawing.Drawing2D.DashCap</string>
        <string>System.Drawing.Drawing2D.DashStyle</string>
        <string>System.Drawing.Drawing2D.FillMode</string>
        <string>System.Drawing.Drawing2D.FlushIntention</string>
        <string>System.Drawing.Drawing2D.GraphicsContainer</string>
        <string>System.Drawing.Drawing2D.GraphicsPath</string>
        <string>System.Drawing.Drawing2D.GraphicsPathIterator</string>
        <string>System.Drawing.Drawing2D.GraphicsState</string>
        <string>System.Drawing.Drawing2D.HatchBrush</string>
        <string>System.Drawing.Drawing2D.HatchStyle</string>
        <string>System.Drawing.Drawing2D.InterpolationMode</string>
        <string>System.Drawing.Drawing2D.LinearGradientBrush</string>
        <string>System.Drawing.Drawing2D.LinearGradientMode</string>
        <string>System.Drawing.Drawing2D.LineCap</string>
        <string>System.Drawing.Drawing2D.LineJoin</string>
        <string>System.Drawing.Drawing2D.Matrix</string>
        <string>System.Drawing.Drawing2D.MatrixOrder</string>
        <string>System.Drawing.Drawing2D.PathData</string>
        <string>System.Drawing.Drawing2D.PathGradientBrush</string>
        <string>System.Drawing.Drawing2D.PathPointType</string>
        <string>System.Drawing.Drawing2D.PenAlignment</string>
        <string>System.Drawing.Drawing2D.PenType</string>
        <string>System.Drawing.Drawing2D.PixelOffsetMode</string>
        <string>System.Drawing.Drawing2D.QualityMode</string>
        <string>System.Drawing.Drawing2D.RegionData</string>
        <string>System.Drawing.Drawing2D.SmoothingMode</string>
        <string>System.Drawing.Drawing2D.WarpMode</string>
        <string>System.Drawing.Drawing2D.WrapMode</string>
        <string>System.Drawing.Font</string>
        <string>System.Drawing.FontConverter</string>
        <string>System.Drawing.FontConverter+FontNameConverter</string>
        <string>System.Drawing.FontConverter+FontUnitConverter</string>
        <string>System.Drawing.FontFamily</string>
        <string>System.Drawing.FontStyle</string>
        <string>System.Drawing.Graphics</string>
        <string>System.Drawing.Graphics+DrawImageAbort</string>
        <string>System.Drawing.Graphics+EnumerateMetafileProc</string>
        <string>System.Drawing.GraphicsUnit</string>
        <string>System.Drawing.Icon</string>
        <string>System.Drawing.IconConverter</string>
        <string>System.Drawing.IDeviceContext</string>
        <string>System.Drawing.Image</string>
        <string>System.Drawing.Image+GetThumbnailImageAbort</string>
        <string>System.Drawing.ImageAnimator</string>
        <string>System.Drawing.ImageConverter</string>
        <string>System.Drawing.ImageFormatConverter</string>
        <string>System.Drawing.Imaging.BitmapData</string>
        <string>System.Drawing.Imaging.ColorAdjustType</string>
        <string>System.Drawing.Imaging.ColorChannelFlag</string>
        <string>System.Drawing.Imaging.ColorMap</string>
        <string>System.Drawing.Imaging.ColorMapType</string>
        <string>System.Drawing.Imaging.ColorMatrix</string>
        <string>System.Drawing.Imaging.ColorMatrixFlag</string>
        <string>System.Drawing.Imaging.ColorMode</string>
        <string>System.Drawing.Imaging.ColorPalette</string>
        <string>System.Drawing.Imaging.EmfPlusRecordType</string>
        <string>System.Drawing.Imaging.EmfType</string>
        <string>System.Drawing.Imaging.Encoder</string>
        <string>System.Drawing.Imaging.EncoderParameter</string>
        <string>System.Drawing.Imaging.EncoderParameters</string>
        <string>System.Drawing.Imaging.EncoderParameterValueType</string>
        <string>System.Drawing.Imaging.EncoderValue</string>
        <string>System.Drawing.Imaging.FrameDimension</string>
        <string>System.Drawing.Imaging.ImageAttributes</string>
        <string>System.Drawing.Imaging.ImageCodecFlags</string>
        <string>System.Drawing.Imaging.ImageCodecInfo</string>
        <string>System.Drawing.Imaging.ImageFlags</string>
        <string>System.Drawing.Imaging.ImageFormat</string>
        <string>System.Drawing.Imaging.ImageLockMode</string>
        <string>System.Drawing.Imaging.Metafile</string>
        <string>System.Drawing.Imaging.MetafileFrameUnit</string>
        <string>System.Drawing.Imaging.MetafileHeader</string>
        <string>System.Drawing.Imaging.MetafileType</string>
        <string>System.Drawing.Imaging.MetaHeader</string>
        <string>System.Drawing.Imaging.PaletteFlags</string>
        <string>System.Drawing.Imaging.PixelFormat</string>
        <string>System.Drawing.Imaging.PlayRecordCallback</string>
        <string>System.Drawing.Imaging.PropertyItem</string>
        <string>System.Drawing.Imaging.WmfPlaceableFileHeader</string>
        <string>System.Drawing.KnownColor</string>
        <string>System.Drawing.Pen</string>
        <string>System.Drawing.Pens</string>
        <string>System.Drawing.Point</string>
        <string>System.Drawing.PointConverter</string>
        <string>System.Drawing.PointF</string>
        <string>System.Drawing.Printing.Duplex</string>
        <string>System.Drawing.Printing.InvalidPrinterException</string>
        <string>System.Drawing.Printing.Margins</string>
        <string>System.Drawing.Printing.MarginsConverter</string>
        <string>System.Drawing.Printing.PageSettings</string>
        <string>System.Drawing.Printing.PaperKind</string>
        <string>System.Drawing.Printing.PaperSize</string>
        <string>System.Drawing.Printing.PaperSource</string>
        <string>System.Drawing.Printing.PaperSourceKind</string>
        <string>System.Drawing.Printing.PreviewPageInfo</string>
        <string>System.Drawing.Printing.PreviewPrintController</string>
        <string>System.Drawing.Printing.PrintAction</string>
        <string>System.Drawing.Printing.PrintController</string>
        <string>System.Drawing.Printing.PrintDocument</string>
        <string>System.Drawing.Printing.PrinterResolution</string>
        <string>System.Drawing.Printing.PrinterResolutionKind</string>
        <string>System.Drawing.Printing.PrinterSettings</string>
        <string>System.Drawing.Printing.PrinterSettings+PaperSizeCollection</string>
        <string>System.Drawing.Printing.PrinterSettings+PaperSourceCollection</string>
        <string>System.Drawing.Printing.PrinterSettings+PrinterResolutionCollection</string>
        <string>System.Drawing.Printing.PrinterSettings+StringCollection</string>
        <string>System.Drawing.Printing.PrinterUnit</string>
        <string>System.Drawing.Printing.PrinterUnitConvert</string>
        <string>System.Drawing.Printing.PrintEventArgs</string>
        <string>System.Drawing.Printing.PrintEventHandler</string>
        <string>System.Drawing.Printing.PrintingPermission</string>
        <string>System.Drawing.Printing.PrintingPermissionAttribute</string>
        <string>System.Drawing.Printing.PrintingPermissionLevel</string>
        <string>System.Drawing.Printing.PrintPageEventArgs</string>
        <string>System.Drawing.Printing.PrintPageEventHandler</string>
        <string>System.Drawing.Printing.PrintRange</string>
        <string>System.Drawing.Printing.QueryPageSettingsEventArgs</string>
        <string>System.Drawing.Printing.QueryPageSettingsEventHandler</string>
        <string>System.Drawing.Printing.StandardPrintController</string>
        <string>System.Drawing.Rectangle</string>
        <string>System.Drawing.RectangleConverter</string>
        <string>System.Drawing.RectangleF</string>
        <string>System.Drawing.Region</string>
        <string>System.Drawing.RotateFlipType</string>
        <string>System.Drawing.Size</string>
        <string>System.Drawing.SizeConverter</string>
        <string>System.Drawing.SizeF</string>
        <string>System.Drawing.SizeFConverter</string>
        <string>System.Drawing.SolidBrush</string>
        <string>System.Drawing.StringAlignment</string>
        <string>System.Drawing.StringDigitSubstitute</string>
        <string>System.Drawing.StringFormat</string>
        <string>System.Drawing.StringFormatFlags</string>
        <string>System.Drawing.StringTrimming</string>
        <string>System.Drawing.StringUnit</string>
        <string>System.Drawing.SystemBrushes</string>
        <string>System.Drawing.SystemColors</string>
        <string>System.Drawing.SystemFonts</string>
        <string>System.Drawing.SystemIcons</string>
        <string>System.Drawing.SystemPens</string>
        <string>System.Drawing.Text.FontCollection</string>
        <string>System.Drawing.Text.GenericFontFamilies</string>
        <string>System.Drawing.Text.HotkeyPrefix</string>
        <string>System.Drawing.Text.InstalledFontCollection</string>
        <string>System.Drawing.Text.PrivateFontCollection</string>
        <string>System.Drawing.Text.TextRenderingHint</string>
        <string>System.Drawing.TextureBrush</string>
        <string>System.Drawing.ToolboxBitmapAttribute</string>
    </TypeNameSkipList>
    <TypeNameWhiteList>
        <string>System.Drawing.Size</string>
    </TypeNameWhiteList>
	<OutputFileDeleteList>
	</OutputFileDeleteList>
	<ReferenceList>
		<string>..\..\Mono.mscorlib\Mono.mscorlib\mscorlib.xml</string>
        <string>..\..\Mono.System\Mono.System\System.xml</string>
	</ReferenceList>
</ConfigObjC>
